rgb_display/__init__.py
rgb_display/hx8353.py
rgb_display/hx8357.py
rgb_display/ili9341.py
rgb_display/rgb.py
rgb_display/s6d02a1.py
rgb_display/ssd1331.py
rgb_display/ssd1351.py
rgb_display/st7735.py
rgb_display/st7789.py
rgb_display-0.0.5.dist-info/LICENSE
rgb_display-0.0.5.dist-info/METADATA
rgb_display-0.0.5.dist-info/WHEEL
rgb_display-0.0.5.dist-info/top_level.txt
rgb_display-0.0.5.dist-info/RECORD
