Metadata-Version: 2.1
Name: rgb-display
Version: 0.0.5
Summary: Portable library for RGB displays.
Home-page: https://github.com/jrmoserbaltimore/RGB_Display
Author: Radomir Dopieralski, Michael McWethy, John Moser
Author-email: john.r.moser@gmail.com
License: MIT
Keywords: adafruit rgb display hx8353 ili9341 s6d02A1 ssd1331 ssd1351 st7735hardware micropython circuitpython
Platform: UNKNOWN
Classifier: Development Status :: 3 - Alpha
Classifier: Intended Audience :: Developers
Classifier: Topic :: Software Development :: Libraries
Classifier: Topic :: System :: Hardware
Classifier: License :: OSI Approved :: MIT License
Classifier: Programming Language :: Python :: 3
Classifier: Programming Language :: Python :: 3.4
Classifier: Programming Language :: Python :: 3.5
Classifier: Programming Language :: Python :: 3.6
Classifier: Programming Language :: Python :: 3.7
Classifier: Programming Language :: Python :: 3.8
Classifier: Programming Language :: Python :: 3.9
Classifier: Programming Language :: Python :: Implementation :: CPython
Classifier: Programming Language :: Python :: Implementation :: MicroPython
